agentctl/__init__.py
agentctl/main.py
agentctl-0.0.1a1.dist-info/METADATA
agentctl-0.0.1a1.dist-info/WHEEL
agentctl-0.0.1a1.dist-info/top_level.txt
agentctl-0.0.1a1.dist-info/RECORD
